liqui_speak/__init__.py
liqui_speak/audio/__init__.py
liqui_speak/audio/converter.py
liqui_speak/audio/formats.py
liqui_speak/cli/__init__.py
liqui_speak/cli/commands.py
liqui_speak/core/__init__.py
liqui_speak/core/config.py
liqui_speak/core/transcription.py
liqui_speak/models/__init__.py
liqui_speak/models/base.py
liqui_speak/models/downloader.py
liqui_speak/models/wrapper.py
liqui_speak/platform/__init__.py
liqui_speak/platform/detector.py
liqui_speak/setup/__init__.py
liqui_speak/setup/manager.py
liqui_speak/setup/shortcut_template.py
liqui_speak-0.3.1.dist-info/WHEEL
liqui_speak-0.3.1.dist-info/entry_points.txt
liqui_speak-0.3.1.dist-info/METADATA
liqui_speak-0.3.1.dist-info/RECORD
