Metadata-Version: 2.3
Name: liqui-speak
Version: 0.3.1
Summary: One-command setup for real-time audio transcription with LFM2.5-Audio model
Author: abhishekbhakat
Author-email: abhishekbhakat <abhishek.bhakat@hotmail.com>
Requires-Dist: pydub>=0.25.0
Requires-Dist: huggingface-hub>=1.2.0
Requires-Dist: python-magic>=0.4.27
Requires-Dist: ruff>=0.5.0 ; extra == 'dev'
Requires-Dist: pyright>=1.1.350 ; extra == 'dev'
Requires-Dist: flake8>=7.0.0 ; extra == 'dev'
Requires-Dist: flake8-import-order>=0.18.2 ; extra == 'dev'
Requires-Dist: black>=24.0.0 ; extra == 'dev'
Requires-Python: >=3.12
Provides-Extra: dev
